amr_x2_pose/__init__.py
amr_x2_pose/main.py
amr_x2_pose/config/__init__.py
amr_x2_pose/config/settings.py
amr_x2_pose/processing/__init__.py
amr_x2_pose/processing/image_enhancement.py
amr_x2_pose/tracking/__init__.py
amr_x2_pose/tracking/kalman_filter.py
amr_x2_pose/tracking/landmark_tracker.py
amr_x2_pose/tracking/multi_hypothesis.py
amr_x2_pose/utils/__init__.py
amr_x2_pose/utils/occlusion_utils.py
amr_x2_pose/utils/pose_utils.py
amr_x2_pose/visualization/__init__.py
amr_x2_pose/visualization/pose_visualizer.py
amr_x2_pose-0.1.1.dist-info/METADATA
amr_x2_pose-0.1.1.dist-info/WHEEL
amr_x2_pose-0.1.1.dist-info/entry_points.txt
amr_x2_pose-0.1.1.dist-info/top_level.txt
amr_x2_pose-0.1.1.dist-info/RECORD
