Metadata-Version: 2.2
Name: amr_x2_pose
Version: 0.1.1
Author: AMR
Author-email: your.email@example.com
License: MIT
Keywords: pose-estimation 3d-pose mediapipe computer-vision
Classifier: Development Status :: 3 - Alpha
Classifier: Intended Audience :: Developers
Classifier: Intended Audience :: Science/Research
Classifier: License :: OSI Approved :: MIT License
Classifier: Programming Language :: Python :: 3
Classifier: Programming Language :: Python :: 3.8
Classifier: Programming Language :: Python :: 3.9
Classifier: Programming Language :: Python :: 3.10
Classifier: Topic :: Scientific/Engineering :: Image Processing
Classifier: Topic :: Scientific/Engineering :: Artificial Intelligence
Classifier: Operating System :: OS Independent
Requires-Python: >=3.8
Requires-Dist: opencv-python
Requires-Dist: mediapipe
Requires-Dist: numpy
Requires-Dist: matplotlib
Requires-Dist: filterpy
Dynamic: author
Dynamic: author-email
Dynamic: classifier
Dynamic: description
Dynamic: description-content-type
Dynamic: keywords
Dynamic: license
Dynamic: requires-dist
Dynamic: requires-python
